fastapi_async_sqla.py
FastAPI_Async_SQLA-0.2.3.dist-info/LICENSE
FastAPI_Async_SQLA-0.2.3.dist-info/METADATA
FastAPI_Async_SQLA-0.2.3.dist-info/WHEEL
FastAPI_Async_SQLA-0.2.3.dist-info/top_level.txt
FastAPI_Async_SQLA-0.2.3.dist-info/RECORD
