Metadata-Version: 2.2
Name: FastAPI-Async-SQLA
Version: 0.2.3
Summary: SQLAlchemy extension for FastAPI with support for asynchronous SQLAlchemy sessions and pagination.
Author-email: Hadrien David <bonjour@hadriendavid.com>
License: MIT License
Project-URL: Homepage, https://github.com/hadrien/fastapi-async-sqla
Project-URL: Documentation, https://github.com/hadrien/fastapi-async-sqla
Project-URL: Repository, https://github.com/hadrien/fastapi-async-sqla
Project-URL: Issues, https://github.com/hadrien/fastapi-async-sqla/issues
Project-URL: Changelog, https://github.com/hadrien/fastapi-async-sqla/releases
Keywords: FastAPI,SQLAlchemy,AsyncIO
Classifier: Development Status :: 4 - Beta
Classifier: Environment :: Web Environment
Classifier: Framework :: AsyncIO
Classifier: Framework :: FastAPI
Classifier: Framework :: Pydantic :: 2
Classifier: Framework :: Pydantic
Classifier: Intended Audience :: Developers
Classifier: Intended Audience :: Information Technology
Classifier: Intended Audience :: System Administrators
Classifier: License :: OSI Approved :: MIT License
Classifier: Operating System :: OS Independent
Classifier: Programming Language :: Python :: 3 :: Only
Classifier: Programming Language :: Python :: 3.12
Classifier: Programming Language :: Python :: 3
Classifier: Programming Language :: Python
Classifier: Programming Language :: SQL
Classifier: Topic :: Internet :: WWW/HTTP :: HTTP Servers
Classifier: Topic :: Internet :: WWW/HTTP
Classifier: Topic :: Internet
Classifier: Topic :: Software Development :: Libraries :: Application Frameworks
Classifier: Topic :: Software Development :: Libraries :: Python Modules
Classifier: Topic :: Software Development :: Libraries
Classifier: Topic :: Software Development
Classifier: Typing :: Typed
Requires-Python: >=3.12
License-File: LICENSE
Requires-Dist: fastapi>=0.115.6
Requires-Dist: sqlalchemy[asyncio]<3,>=2.0.34
Requires-Dist: structlog>=24.4.0
